{
  "_class": "group",
  "booleanOperation": 0,
  "clippingMaskMode": 0,
  "do_objectID": "20450FEF-134B-4F42-997D-981299D8A02E",
  "exportOptions": {
    "_class": "exportOptions",
    "do_objectID": "2FD60595-F555-4CAA-9142-ADB487663BDB",
    "exportFormats": [
    ],
    "includedLayerIds": [
    ],
    "layerOptions": 0,
    "shouldTrim": false
  },
  "frame": {
    "_class": "rect",
    "constrainProportions": true,
    "do_objectID": "060C8AA1-708C-4B4A-9CF8-AD069246ECA1",
    "height": 16,
    "width": 112,
    "x": 192,
    "y": 492
  },
  "hasClickThrough": false,
  "hasClippingMask": false,
  "isFixedToViewport": false,
  "isFlippedHorizontal": false,
  "isFlippedVertical": false,
  "isLocked": false,
  "isVisible": true,
  "layerListExpandedType": 2,
  "layers": [
    {
      "class": "symbolInstance",
      "id": "35CA5F95-B15F-406C-8CDB-833F0D7245BB"
    },
    {
      "class": "symbolInstance",
      "id": "647D4179-7EF7-4D58-AB09-5734C21E838D"
    },
    {
      "class": "symbolInstance",
      "id": "ED4B75D1-2F49-483A-91EE-C32C96159DD1"
    },
    {
      "class": "symbolInstance",
      "id": "E2D0A756-0286-471B-8A75-5887B25DA2AC"
    },
    {
      "class": "symbolInstance",
      "id": "990CB597-4D60-4126-BA82-DD9DDFA15BEE"
    }
  ],
  "name": "stars",
  "nameIsFixed": true,
  "resizingConstraint": 63,
  "resizingType": 0,
  "rotation": 0,
  "shouldBreakMaskChain": false,
  "style": {
    "_class": "style",
    "do_objectID": "21C8E739-8B84-45CC-80C5-FD61979CA30C",
    "endMarkerType": 0,
    "miterLimit": 10,
    "startMarkerType": 0,
    "windingRule": 1
  }
}