{
  "_class": "symbolMaster",
  "backgroundColor": {
    "_class": "color",
    "alpha": 1,
    "blue": 1,
    "do_objectID": "DDB01C66-FE29-4E10-AC2F-B2EC872C9F10",
    "green": 1,
    "red": 1
  },
  "booleanOperation": -1,
  "changeIdentifier": 856,
  "clippingMaskMode": 0,
  "do_objectID": "5F997E3E-A04C-4A09-B15C-02FB01589BBB",
  "exportOptions": {
    "_class": "exportOptions",
    "do_objectID": "9B752810-8AA4-4495-A576-3BC3D83FB9F7",
    "exportFormats": [
      {
        "_class": "exportFormat",
        "absoluteSize": 0,
        "fileFormat": "svg",
        "name": "",
        "namingScheme": 0,
        "scale": 1,
        "visibleScaleType": 0
      }
    ],
    "includedLayerIds": [
    ],
    "layerOptions": 0,
    "shouldTrim": false
  },
  "frame": {
    "_class": "rect",
    "constrainProportions": false,
    "do_objectID": "8FC631F9-7162-45A4-BD17-BEC7424F227C",
    "height": 144,
    "width": 144,
    "x": 9379,
    "y": -4062
  },
  "hasBackgroundColor": false,
  "hasClickThrough": false,
  "hasClippingMask": false,
  "horizontalRulerData": {
    "_class": "rulerData",
    "base": 0,
    "do_objectID": "613FB7E7-7B5D-4152-A8B2-97C151C87EDA",
    "guides": [
    ]
  },
  "includeBackgroundColorInExport": true,
  "includeBackgroundColorInInstance": false,
  "includeInCloudUpload": true,
  "isFixedToViewport": false,
  "isFlippedHorizontal": false,
  "isFlippedVertical": false,
  "isFlowHome": false,
  "isLocked": false,
  "isVisible": true,
  "layerListExpandedType": 2,
  "layers": [
    {
      "class": "shapeGroup",
      "id": "9CA43E6E-2BB1-46D6-A84C-8D94BDF25BAD"
    }
  ],
  "name": "Icons/Line/Actions/Plus",
  "nameIsFixed": true,
  "resizesContent": false,
  "resizingConstraint": 63,
  "resizingType": 0,
  "rotation": 0,
  "shouldBreakMaskChain": true,
  "style": {
    "_class": "style",
    "do_objectID": "C16617C2-163D-4CF0-999E-B0BBAA15A7C5",
    "endMarkerType": 0,
    "miterLimit": 10,
    "startMarkerType": 0,
    "windingRule": 1
  },
  "symbolID": "DE10C4DD-80E6-4BC3-A42D-BA720DD254D4",
  "verticalRulerData": {
    "_class": "rulerData",
    "base": 0,
    "do_objectID": "FB4CFD3E-226E-43DB-A123-C84D4A0B7411",
    "guides": [
    ]
  }
}