{
  "_class": "text",
  "attributedString": {
    "_class": "attributedString",
    "attributes": [
      {
        "_class": "stringAttribute",
        "attributes": {
          "MSAttributedStringColorAttribute": {
            "_class": "color",
            "alpha": 0.54,
            "blue": 0,
            "green": 0,
            "red": 0
          },
          "MSAttributedStringFontAttribute": {
            "_class": "fontDescriptor",
            "attributes": {
              "name": "HelveticaNeue-Medium",
              "size": 12
            }
          },
          "paragraphStyle": {
            "_class": "paragraphStyle",
            "alignment": 0
          },
          "textStyleVerticalAlignmentKey": 0
        },
        "length": 13,
        "location": 0
      }
    ],
    "string": "1824080900001"
  },
  "automaticallyDrawOnUnderlyingPath": false,
  "booleanOperation": -1,
  "clippingMaskMode": 0,
  "do_objectID": "E3E84ACB-7EC7-49E2-A686-F56E6BFD2121",
  "dontSynchroniseWithSymbol": false,
  "exportOptions": {
    "_class": "exportOptions",
    "do_objectID": "BD39E102-F1F6-4CB3-9BB2-0F18F995821B",
    "exportFormats": [
    ],
    "includedLayerIds": [
    ],
    "layerOptions": 0,
    "shouldTrim": false
  },
  "frame": {
    "_class": "rect",
    "constrainProportions": false,
    "do_objectID": "8FE1DE88-B6A1-48FD-87ED-EA01F14A238F",
    "height": 16,
    "width": 100,
    "x": 108,
    "y": 16
  },
  "glyphBounds": "{{0, 3}, {85, 10}}",
  "hasClippingMask": false,
  "isFixedToViewport": false,
  "isFlippedHorizontal": false,
  "isFlippedVertical": false,
  "isLocked": false,
  "isVisible": true,
  "layerListExpandedType": 0,
  "lineSpacingBehaviour": 2,
  "name": "1824080900001",
  "nameIsFixed": false,
  "resizingConstraint": 47,
  "resizingType": 0,
  "rotation": 0,
  "shouldBreakMaskChain": false,
  "style": {
    "_class": "style",
    "do_objectID": "986BD2DB-BFFF-4A70-BF51-CCBBDFC21A4D",
    "endMarkerType": 0,
    "miterLimit": 10,
    "startMarkerType": 0,
    "textStyle": {
      "_class": "textStyle",
      "do_objectID": "8E912910-3F5B-4349-8531-655C0E682F39",
      "encodedAttributes": {
        "MSAttributedStringColorAttribute": {
          "_class": "color",
          "alpha": 0.54,
          "blue": 0,
          "green": 0,
          "red": 0
        },
        "MSAttributedStringFontAttribute": {
          "_class": "fontDescriptor",
          "attributes": {
            "name": "HelveticaNeue-Medium",
            "size": 12
          }
        },
        "paragraphStyle": {
          "_class": "paragraphStyle",
          "alignment": 0
        },
        "textStyleVerticalAlignmentKey": 0
      },
      "verticalAlignment": 1
    },
    "windingRule": 1
  },
  "textBehaviour": 2
}