{
  "_class": "group",
  "booleanOperation": -1,
  "clippingMaskMode": 0,
  "do_objectID": "1191F74D-3BDC-4911-A1DE-644EED255607",
  "exportOptions": {
    "_class": "exportOptions",
    "do_objectID": "5CB314F1-617B-4835-88D3-001EE3CFB1F5",
    "exportFormats": [
    ],
    "includedLayerIds": [
    ],
    "layerOptions": 0,
    "shouldTrim": false
  },
  "frame": {
    "_class": "rect",
    "constrainProportions": false,
    "do_objectID": "7504AC5B-0E1E-41DA-AFC9-3DE414A74E8D",
    "height": 27,
    "width": 320,
    "x": 0,
    "y": 0
  },
  "hasClickThrough": false,
  "hasClippingMask": false,
  "isFixedToViewport": false,
  "isFlippedHorizontal": false,
  "isFlippedVertical": false,
  "isLocked": false,
  "isVisible": true,
  "layerListExpandedType": 0,
  "layers": [
    {
      "class": "rectangle",
      "id": "518E79E0-7368-4FBE-9367-19862EC19414"
    },
    {
      "class": "text",
      "id": "1EB8B6E2-947D-4D55-A065-18D02E83C8D0"
    }
  ],
  "name": "Group",
  "nameIsFixed": false,
  "resizingConstraint": 63,
  "resizingType": 0,
  "rotation": 0,
  "shouldBreakMaskChain": false,
  "style": {
    "_class": "style",
    "do_objectID": "86D11447-6A41-4D19-B94B-869B53B0539E",
    "endMarkerType": 0,
    "miterLimit": 10,
    "startMarkerType": 0,
    "windingRule": 1
  }
}