{
  "_class": "symbolMaster",
  "backgroundColor": {
    "_class": "color",
    "alpha": 1,
    "blue": 1,
    "do_objectID": "01D970B5-C2FD-40F3-8301-77AA480060E0",
    "green": 1,
    "red": 1
  },
  "booleanOperation": -1,
  "changeIdentifier": 13415,
  "clippingMaskMode": 0,
  "do_objectID": "B88E477B-B5C2-4725-B4E7-2682DB1A1577",
  "exportOptions": {
    "_class": "exportOptions",
    "do_objectID": "A07D79C3-4F82-4668-BC3C-1C17A22FE6FE",
    "exportFormats": [
      {
        "_class": "exportFormat",
        "absoluteSize": 0,
        "fileFormat": "svg",
        "name": "",
        "namingScheme": 0,
        "scale": 1,
        "visibleScaleType": 0
      }
    ],
    "includedLayerIds": [
    ],
    "layerOptions": 0,
    "shouldTrim": false
  },
  "frame": {
    "_class": "rect",
    "constrainProportions": false,
    "do_objectID": "57F0A814-5031-4E96-AE6F-D3EC24CCE3DF",
    "height": 144,
    "width": 144,
    "x": 4736,
    "y": -4062
  },
  "hasBackgroundColor": false,
  "hasClickThrough": true,
  "hasClippingMask": false,
  "horizontalRulerData": {
    "_class": "rulerData",
    "base": 0,
    "do_objectID": "4FBD74D9-7811-44AA-860F-BB62FCF63FB9",
    "guides": [
    ]
  },
  "includeBackgroundColorInExport": true,
  "includeBackgroundColorInInstance": false,
  "includeInCloudUpload": true,
  "isFixedToViewport": false,
  "isFlippedHorizontal": false,
  "isFlippedVertical": false,
  "isFlowHome": false,
  "isLocked": false,
  "isVisible": true,
  "layerListExpandedType": 2,
  "layers": [
    {
      "class": "shapeGroup",
      "id": "B4E27D8D-8072-423D-B229-3BFF82946557"
    }
  ],
  "name": "Icons/Line/Actions/Empty Search",
  "nameIsFixed": true,
  "resizesContent": false,
  "resizingConstraint": 63,
  "resizingType": 0,
  "rotation": 0,
  "shouldBreakMaskChain": true,
  "style": {
    "_class": "style",
    "do_objectID": "479CEFD9-2267-4DDB-B08E-D98D1C92191D",
    "endMarkerType": 0,
    "miterLimit": 10,
    "startMarkerType": 0,
    "windingRule": 1
  },
  "symbolID": "2DED8D77-E900-46EB-B9A7-DD178F57055E",
  "verticalRulerData": {
    "_class": "rulerData",
    "base": 0,
    "do_objectID": "B41F403E-8196-42EC-AE3F-A2EC40F4EBB3",
    "guides": [
    ]
  }
}