{
  "_class": "shapePath",
  "booleanOperation": -1,
  "clippingMaskMode": 0,
  "do_objectID": "48AA4979-4C2C-4ED4-91BC-0CE15827E992",
  "edited": true,
  "exportOptions": {
    "_class": "exportOptions",
    "do_objectID": "F6AE6D80-5BE5-46B0-866F-1A0E986D4B3B",
    "exportFormats": [
    ],
    "includedLayerIds": [
    ],
    "layerOptions": 0,
    "shouldTrim": false
  },
  "frame": {
    "_class": "rect",
    "constrainProportions": false,
    "do_objectID": "CD97AFE8-7060-45F4-99CD-F7EBB9234B1E",
    "height": 5,
    "width": 5,
    "x": 104,
    "y": 27
  },
  "hasClippingMask": false,
  "isClosed": true,
  "isFixedToViewport": false,
  "isFlippedHorizontal": false,
  "isFlippedVertical": false,
  "isLocked": false,
  "isVisible": true,
  "layerListExpandedType": 0,
  "name": "Path",
  "nameIsFixed": false,
  "pointRadiusBehaviour": 0,
  "points": [
    {
      "_class": "curvePoint",
      "cornerRadius": 0,
      "curveFrom": "{0.14074074074073906, 1}",
      "curveMode": 1,
      "curveTo": "{0.14074074074073906, 1}",
      "hasCurveFrom": false,
      "hasCurveTo": false,
      "point": "{0.14074074074073906, 1}"
    },
    {
      "_class": "curvePoint",
      "cornerRadius": 0,
      "curveFrom": "{0, 0.12345679012345645}",
      "curveMode": 1,
      "curveTo": "{0, 0.12345679012345645}",
      "hasCurveFrom": false,
      "hasCurveTo": false,
      "point": "{0, 0.12345679012345645}"
    },
    {
      "_class": "curvePoint",
      "cornerRadius": 0,
      "curveFrom": "{0.91111111111111198, 0}",
      "curveMode": 1,
      "curveTo": "{0.91111111111111198, 0}",
      "hasCurveFrom": false,
      "hasCurveTo": false,
      "point": "{0.91111111111111198, 0}"
    },
    {
      "_class": "curvePoint",
      "cornerRadius": 0,
      "curveFrom": "{1, 0.83333333333333104}",
      "curveMode": 1,
      "curveTo": "{1, 0.83333333333333104}",
      "hasCurveFrom": false,
      "hasCurveTo": false,
      "point": "{1, 0.83333333333333104}"
    },
    {
      "_class": "curvePoint",
      "cornerRadius": 0,
      "curveFrom": "{0.14074074074073906, 1}",
      "curveMode": 1,
      "curveTo": "{0.14074074074073906, 1}",
      "hasCurveFrom": false,
      "hasCurveTo": false,
      "point": "{0.14074074074073906, 1}"
    }
  ],
  "resizingConstraint": 63,
  "resizingType": 0,
  "rotation": 0,
  "shouldBreakMaskChain": false,
  "style": {
    "_class": "style",
    "do_objectID": "F89B2C95-89A4-4F21-A5E8-537C891F4486",
    "endMarkerType": 0,
    "fills": [
      {
        "_class": "fill",
        "color": {
          "_class": "color",
          "alpha": 1,
          "blue": 0.9098039215686274,
          "green": 0.9058823529411765,
          "red": 0.9019607843137255
        },
        "fillType": 0,
        "isEnabled": true,
        "noiseIndex": 0,
        "noiseIntensity": 0,
        "patternFillType": 0,
        "patternTileScale": 1
      }
    ],
    "miterLimit": 10,
    "startMarkerType": 0,
    "windingRule": 1
  }
}