{
  "_class": "shapePath",
  "booleanOperation": -1,
  "clippingMaskMode": 0,
  "do_objectID": "756F9238-6BB3-43FB-8788-819359DA2E94",
  "edited": true,
  "exportOptions": {
    "_class": "exportOptions",
    "do_objectID": "00EA477B-C9B1-4C00-9A42-76BA26949709",
    "exportFormats": [
    ],
    "includedLayerIds": [
    ],
    "layerOptions": 0,
    "shouldTrim": false
  },
  "frame": {
    "_class": "rect",
    "constrainProportions": false,
    "do_objectID": "2853F7DA-E6F1-41C5-97FF-DB1B8201A08F",
    "height": 48.00302723854531,
    "width": 60.02294258204819,
    "x": 445.7149201637231,
    "y": 560.1529722615566
  },
  "hasClippingMask": false,
  "isClosed": true,
  "isFixedToViewport": false,
  "isFlippedHorizontal": false,
  "isFlippedVertical": false,
  "isLocked": false,
  "isVisible": true,
  "layerListExpandedType": 0,
  "name": "Path",
  "nameIsFixed": false,
  "pointRadiusBehaviour": 0,
  "points": [
    {
      "_class": "curvePoint",
      "cornerRadius": 0,
      "curveFrom": "{1, 0.183823529411761}",
      "curveMode": 1,
      "curveTo": "{1, 0.183823529411761}",
      "hasCurveFrom": false,
      "hasCurveTo": false,
      "point": "{1, 0.183823529411761}"
    },
    {
      "_class": "curvePoint",
      "cornerRadius": 0,
      "curveFrom": "{0.86138613861386182, 1}",
      "curveMode": 1,
      "curveTo": "{0.86138613861386182, 1}",
      "hasCurveFrom": false,
      "hasCurveTo": false,
      "point": "{0.86138613861386182, 1}"
    },
    {
      "_class": "curvePoint",
      "cornerRadius": 0,
      "curveFrom": "{0, 0.82352941176470706}",
      "curveMode": 1,
      "curveTo": "{0, 0.82352941176470706}",
      "hasCurveFrom": false,
      "hasCurveTo": false,
      "point": "{0, 0.82352941176470706}"
    },
    {
      "_class": "curvePoint",
      "cornerRadius": 0,
      "curveFrom": "{0.14851485148514845, 0}",
      "curveMode": 1,
      "curveTo": "{0.14851485148514845, 0}",
      "hasCurveFrom": false,
      "hasCurveTo": false,
      "point": "{0.14851485148514845, 0}"
    },
    {
      "_class": "curvePoint",
      "cornerRadius": 0,
      "curveFrom": "{1, 0.183823529411761}",
      "curveMode": 1,
      "curveTo": "{1, 0.183823529411761}",
      "hasCurveFrom": false,
      "hasCurveTo": false,
      "point": "{1, 0.183823529411761}"
    }
  ],
  "resizingConstraint": 63,
  "resizingType": 0,
  "rotation": 0,
  "shouldBreakMaskChain": false,
  "style": {
    "_class": "style",
    "do_objectID": "654CA6E4-AA0C-48C3-8DEE-9264B3BEFAE2",
    "endMarkerType": 0,
    "fills": [
      {
        "_class": "fill",
        "color": {
          "_class": "color",
          "alpha": 1,
          "blue": 0.9098039215686274,
          "green": 0.9058823529411765,
          "red": 0.9019607843137255
        },
        "fillType": 0,
        "isEnabled": true,
        "noiseIndex": 0,
        "noiseIntensity": 0,
        "patternFillType": 0,
        "patternTileScale": 1
      }
    ],
    "miterLimit": 10,
    "startMarkerType": 0,
    "windingRule": 1
  }
}