{
  "_class": "shapePath",
  "booleanOperation": -1,
  "clippingMaskMode": 0,
  "do_objectID": "0242FDCC-F355-4DF9-99BA-365B7EB09A85",
  "edited": true,
  "exportOptions": {
    "_class": "exportOptions",
    "do_objectID": "A3DA5C6D-360C-465B-B111-DA76A6EB6D80",
    "exportFormats": [
    ],
    "includedLayerIds": [
    ],
    "layerOptions": 0,
    "shouldTrim": false
  },
  "frame": {
    "_class": "rect",
    "constrainProportions": false,
    "do_objectID": "7FB72ABF-8F83-4204-97D5-B145C389D3F1",
    "height": 6,
    "width": 5,
    "x": 119,
    "y": 100
  },
  "hasClippingMask": false,
  "isClosed": true,
  "isFixedToViewport": false,
  "isFlippedHorizontal": false,
  "isFlippedVertical": false,
  "isLocked": false,
  "isVisible": true,
  "layerListExpandedType": 0,
  "name": "Path",
  "nameIsFixed": false,
  "pointRadiusBehaviour": 0,
  "points": [
    {
      "_class": "curvePoint",
      "cornerRadius": 0,
      "curveFrom": "{0.93589743589743601, 0.1368421052631591}",
      "curveMode": 1,
      "curveTo": "{0.93589743589743601, 0.1368421052631591}",
      "hasCurveFrom": false,
      "hasCurveTo": false,
      "point": "{0.93589743589743601, 0.1368421052631591}"
    },
    {
      "_class": "curvePoint",
      "cornerRadius": 0,
      "curveFrom": "{1, 0.96842105263157774}",
      "curveMode": 1,
      "curveTo": "{1, 0.96842105263157774}",
      "hasCurveFrom": false,
      "hasCurveTo": false,
      "point": "{1, 0.96842105263157774}"
    },
    {
      "_class": "curvePoint",
      "cornerRadius": 0,
      "curveFrom": "{0, 1}",
      "curveMode": 1,
      "curveTo": "{0, 1}",
      "hasCurveFrom": false,
      "hasCurveTo": false,
      "point": "{0, 1}"
    },
    {
      "_class": "curvePoint",
      "cornerRadius": 0,
      "curveFrom": "{0.012820512820512072, 0}",
      "curveMode": 1,
      "curveTo": "{0.012820512820512072, 0}",
      "hasCurveFrom": false,
      "hasCurveTo": false,
      "point": "{0.012820512820512072, 0}"
    },
    {
      "_class": "curvePoint",
      "cornerRadius": 0,
      "curveFrom": "{0.93589743589743601, 0.1368421052631591}",
      "curveMode": 1,
      "curveTo": "{0.93589743589743601, 0.1368421052631591}",
      "hasCurveFrom": false,
      "hasCurveTo": false,
      "point": "{0.93589743589743601, 0.1368421052631591}"
    }
  ],
  "resizingConstraint": 63,
  "resizingType": 0,
  "rotation": 0,
  "shouldBreakMaskChain": false,
  "style": {
    "_class": "style",
    "do_objectID": "E1AB0708-4867-4252-8532-5F387623A41A",
    "endMarkerType": 0,
    "fills": [
      {
        "_class": "fill",
        "color": {
          "_class": "color",
          "alpha": 1,
          "blue": 0.9098039215686274,
          "green": 0.9058823529411765,
          "red": 0.9019607843137255
        },
        "fillType": 0,
        "isEnabled": true,
        "noiseIndex": 0,
        "noiseIntensity": 0,
        "patternFillType": 0,
        "patternTileScale": 1
      }
    ],
    "miterLimit": 10,
    "startMarkerType": 0,
    "windingRule": 1
  }
}