{
  "_class": "shapePath",
  "booleanOperation": -1,
  "clippingMaskMode": 0,
  "do_objectID": "080E1BFC-6B0C-46FB-873B-8DAC66C95C49",
  "edited": true,
  "exportOptions": {
    "_class": "exportOptions",
    "do_objectID": "4A8A23A0-C8D3-44A5-A8E8-0FF93EC3821F",
    "exportFormats": [
    ],
    "includedLayerIds": [
    ],
    "layerOptions": 0,
    "shouldTrim": false
  },
  "frame": {
    "_class": "rect",
    "constrainProportions": false,
    "do_objectID": "FF47A9FC-D800-413E-BB6B-72A7475E9155",
    "height": 9,
    "width": 5,
    "x": 32,
    "y": 40
  },
  "hasClippingMask": false,
  "isClosed": true,
  "isFixedToViewport": false,
  "isFlippedHorizontal": false,
  "isFlippedVertical": false,
  "isLocked": false,
  "isVisible": true,
  "layerListExpandedType": 0,
  "name": "Path",
  "nameIsFixed": false,
  "pointRadiusBehaviour": 0,
  "points": [
    {
      "_class": "curvePoint",
      "cornerRadius": 0,
      "curveFrom": "{0.53896103896103953, 0}",
      "curveMode": 1,
      "curveTo": "{0.53896103896103953, 0}",
      "hasCurveFrom": false,
      "hasCurveTo": false,
      "point": "{0.53896103896103953, 0}"
    },
    {
      "_class": "curvePoint",
      "cornerRadius": 0,
      "curveFrom": "{1, 0.72834645669291409}",
      "curveMode": 1,
      "curveTo": "{1, 0.72834645669291409}",
      "hasCurveFrom": false,
      "hasCurveTo": false,
      "point": "{1, 0.72834645669291409}"
    },
    {
      "_class": "curvePoint",
      "cornerRadius": 0,
      "curveFrom": "{0.22077922077922107, 1}",
      "curveMode": 1,
      "curveTo": "{0.22077922077922107, 1}",
      "hasCurveFrom": false,
      "hasCurveTo": false,
      "point": "{0.22077922077922107, 1}"
    },
    {
      "_class": "curvePoint",
      "cornerRadius": 0,
      "curveFrom": "{0, 0.6811023622047232}",
      "curveMode": 1,
      "curveTo": "{0, 0.6811023622047232}",
      "hasCurveFrom": false,
      "hasCurveTo": false,
      "point": "{0, 0.6811023622047232}"
    },
    {
      "_class": "curvePoint",
      "cornerRadius": 0,
      "curveFrom": "{0.53896103896103953, 0}",
      "curveMode": 1,
      "curveTo": "{0.53896103896103953, 0}",
      "hasCurveFrom": false,
      "hasCurveTo": false,
      "point": "{0.53896103896103953, 0}"
    }
  ],
  "resizingConstraint": 63,
  "resizingType": 0,
  "rotation": 0,
  "shouldBreakMaskChain": false,
  "style": {
    "_class": "style",
    "do_objectID": "8E45DF80-7901-4D02-ABFE-D22B00D546A2",
    "endMarkerType": 0,
    "fills": [
      {
        "_class": "fill",
        "color": {
          "_class": "color",
          "alpha": 1,
          "blue": 0.9098039215686274,
          "green": 0.9058823529411765,
          "red": 0.9019607843137255
        },
        "fillType": 0,
        "isEnabled": true,
        "noiseIndex": 0,
        "noiseIntensity": 0,
        "patternFillType": 0,
        "patternTileScale": 1
      }
    ],
    "miterLimit": 10,
    "startMarkerType": 0,
    "windingRule": 1
  }
}